tbcp/__init__.py
tbcp/oci_chat_tracker.py
tbcp-0.2.1.dist-info/METADATA
tbcp-0.2.1.dist-info/WHEEL
tbcp-0.2.1.dist-info/top_level.txt
tbcp-0.2.1.dist-info/RECORD
