Metadata-Version: 2.4
Name: tbcp
Version: 0.2.1
Summary: OCI Generative AI monkey-patch for logging input/output/cost
Author-email: Your Name <you@example.com>
Requires-Dist: oci
Requires-Dist: tiktoken
